{"name": "בעקבות_מלחמת_העולם_הראשונה", "id": 1015087, "predecessors": [{"name": "מלחמת_העולם_הראשונה", "id": 18337}, {"name": "מלחמות", "id": 18502}], "successors": [{"name": "מלחמת_האזרחים_ברוסיה", "id": 314643}, {"name": "מלחמת_העצמאות_של_טורקיה", "id": 413864}, {"name": "רפובליקת_ויימאר", "id": 623094}, {"name": "אנדרטאות_למלחמת_העולם_הראשונה", "id": 759466}, {"name": "בעקבות_מלחמת_העולם_הראשונה:_אמנות_והסכמים", "id": 1015088}, {"name": "המדינות_היורשות_של_האימפריה_האוסטרו-הונגרית", "id": 2103638}]}