{"name": "חיילי_צה\"ל_במלחמת_סיני", "id": 1100161, "predecessors": [{"name": "מלחמת_סיני", "id": 1100150}, {"name": "מלחמת_סיני:_אישים", "id": 2090987}, {"name": "אנשי_צבא", "id": 135579}], "successors": [{"name": "מפקדי_חטיבות_במלחמת_סיני", "id": 2284271}, {"name": "מפקדי_פלוגות_במלחמת_סיני", "id": 2284739}, {"name": "מפקדי_גדודים_במלחמת_סיני", "id": 2284924}, {"name": "מפקדי_מחלקות_במלחמת_סיני", "id": 2284937}, {"name": "חברי_המטה_הכללי_במלחמת_סיני", "id": 2286750}, {"name": "חיילי_חיל_השריון_במלחמת_סיני", "id": 2289526}, {"name": "חיילי_חיל_הרגלים_במלחמת_סיני", "id": 2289528}, {"name": "חיילי_חיל_התותחנים_במלחמת_סיני", "id": 2289536}]}