{"name": "ארצות_הברית:_יחסי_חוץ_לפי_מדינה", "id": 1324104, "predecessors": [{"name": "ארצות_הברית:_יחסי_חוץ", "id": 1090415}, {"name": "יחסים_בין-לאומיים", "id": 132773}], "successors": [{"name": "יחסי_ארצות_הברית_–_ישראל", "id": 817466}, {"name": "יחסי_ארצות_הברית_–_ברית_המועצות", "id": 817482}, {"name": "אמריקאים_ממוצא_יפני", "id": 1419335}, {"name": "אמריקאים_ממוצא_צרפתי", "id": 1388281}, {"name": "רוסים_שהוטלו_עליהם_סנקציות_של_מחלקת_האוצר_של_ארצות_הברית", "id": 2167985}, {"name": "גופים_רוסים_שהוטלו_עליהם_סנקציות_של_מחלקת_האוצר_של_ארצות_הברית", "id": 2219067}, {"name": "אמריקאים_ממוצא_קנדי", "id": 1585557}, {"name": "גבול_ארצות_הברית_–_קנדה", "id": 2349617}, {"name": "אמריקאים_ממוצא_מקסיקני", "id": 1352985}, {"name": "אמריקאים_ממוצא_דרום_קוריאני", "id": 1419538}, {"name": "אנשי_הכוחות_המזוינים_של_ארצות_הברית_במלחמת_ארצות_הברית–מקסיקו", "id": 872297}, {"name": "זירת_אסיה_והאוקיינוס_השקט_במלחמת_העולם_השנייה", "id": 390832}, {"name": "אמריקאים_ממוצא_סיני", "id": 1419542}, {"name": "מלחמת_עיראק", "id": 393044}, {"name": "אמריקאים_ממוצא_הודי", "id": 1419539}, {"name": "אמריקאים_ממוצא_הולנדי", "id": 1409850}, {"name": "אמריקאים_ממוצא_שוודי", "id": 1409853}]}