{"name": "רבנים_אמריקאים", "id": 142626, "predecessors": [{"name": "יהודים_אמריקאים", "id": 285326}, {"name": "היסטוריה", "id": 21852}], "successors": [{"name": "ראשי_ישיבה_אמריקאים", "id": 845600}, {"name": "רבנים_צבאיים_אמריקאים", "id": 1163769}, {"name": "מחברי_ספרי_שו\"ת_אמריקאים", "id": 1424536}, {"name": "שיקגו:_רבנים", "id": 1094122}, {"name": "ניו_יורק:_רבנים", "id": 1399542}, {"name": "בולטימור:_רבנים", "id": 1872175}, {"name": "בוסטון:_רבנים", "id": 1872180}, {"name": "רבנים_חרדים_אמריקאים", "id": 412813}, {"name": "רבנים_רפורמים_אמריקאים", "id": 920324}, {"name": "רבנים_קונסרבטיבים_אמריקאים", "id": 1872272}]}