{"name": "אירופה:_ארגונים", "id": 1534513, "predecessors": [{"name": "אירופה", "id": 35355}, {"name": "ארגונים", "id": 23279}], "successors": [{"name": "האיחוד_האירופי", "id": 34443}, {"name": "CERN", "id": 584221}, {"name": "מדינות_החברות_במועצת_אירופה", "id": 1532049}, {"name": "חברות_גרמניות", "id": 34678}, {"name": "חברות_הונגריות", "id": 158233}, {"name": "חברות_בריטיות", "id": 162638}, {"name": "חברות_רוסיות", "id": 197885}, {"name": "חברות_איטלקיות", "id": 241586}, {"name": "חברות_צרפתיות", "id": 272791}, {"name": "חברות_ספרדיות", "id": 319414}, {"name": "חברות_הולנדיות", "id": 333726}, {"name": "חברות_שווייצריות", "id": 390846}, {"name": "חברות_אוקראיניות", "id": 660404}, {"name": "חברות_אוסטריות", "id": 691532}, {"name": "חברות_שוודיות", "id": 810336}, {"name": "חברות_תעופה_טורקיות", "id": 810067}]}