{"name": "הרי_אילת", "id": 1542620, "predecessors": [{"name": "ארץ_ישראל:_אזורים", "id": 282882}, {"name": "הנגב:_הרים", "id": 553057}, {"name": "ישראל:_גאוגרפיה", "id": 1418331}, {"name": "ישראל:_הרים", "id": 1418706}, {"name": "ישראל:_רכסי_הרים", "id": 1418700}, {"name": "שביל_ישראל", "id": 159760}], "successors": [{"name": "כביש_12", "id": 2067266}, {"name": "הרי_אילת:_נחלים", "id": 2227800}, {"name": "אילת:_תחבורה", "id": 975160}, {"name": "אילת:_מבנים", "id": 1036784}, {"name": "אילת:_אישים", "id": 1075740}, {"name": "אילת:_היסטוריה", "id": 1075745}, {"name": "אילת:_גאוגרפיה", "id": 1566389}, {"name": "כדורסלני_הפועל_אילת", "id": 674185}, {"name": "מאמני_הפועל_אילת", "id": 1285638}, {"name": "אילת:_בתי_מלון", "id": 778150}, {"name": "אילת:_אטרקציות", "id": 1594161}]}