{"name": "אישים_שחיו_במאה_ה-18", "id": 1616451, "predecessors": [{"name": "המאה_ה-18", "id": 47211}, {"name": "אלפים", "id": 177700}, {"name": "העת_החדשה_המוקדמת", "id": 1637306}, {"name": "מאות", "id": 46374}], "successors": [{"name": "נפטרים_ב-1800", "id": 1582465}, {"name": "נפטרים_ב-1701", "id": 1583065}, {"name": "נפטרים_ב-1702", "id": 1583066}, {"name": "נפטרים_ב-1703", "id": 1583377}, {"name": "נפטרים_ב-1704", "id": 1583378}, {"name": "נפטרים_ב-1705", "id": 1583379}, {"name": "נפטרים_ב-1706", "id": 1583380}, {"name": "נפטרים_ב-1707", "id": 1583381}, {"name": "נפטרים_ב-1708", "id": 1583382}, {"name": "נפטרים_ב-1709", "id": 1583383}, {"name": "נפטרים_ב-1711", "id": 1583385}, {"name": "נפטרים_ב-1712", "id": 1583386}, {"name": "נפטרים_ב-1714", "id": 1583388}, {"name": "נפטרים_ב-1715", "id": 1583389}, {"name": "נפטרים_ב-1716", "id": 1583390}, {"name": "נפטרים_ב-1718", "id": 1583392}, {"name": "נפטרים_ב-1719", "id": 1583393}, {"name": "נפטרים_ב-1720", "id": 1583394}, {"name": "נפטרים_ב-1721", "id": 1583395}, {"name": "נפטרים_ב-1722", "id": 1583396}, {"name": "נפטרים_ב-1723", "id": 1583397}, {"name": "נפטרים_ב-1724", "id": 1583398}, {"name": "נפטרים_ב-1726", "id": 1583400}, {"name": "נפטרים_ב-1727", "id": 1583401}, {"name": "נפטרים_ב-1728", "id": 1583402}, {"name": "נפטרים_ב-1729", "id": 1583403}, {"name": "נפטרים_ב-1730", "id": 1583404}, {"name": "נפטרים_ב-1731", "id": 1583405}, {"name": "נפטרים_ב-1732", "id": 1583406}, {"name": "נפטרים_ב-1733", "id": 1583407}, {"name": "נפטרים_ב-1735", "id": 1583409}, {"name": "נפטרים_ב-1736", "id": 1583410}, {"name": "נפטרים_ב-1739", "id": 1583413}, {"name": "נפטרים_ב-1740", "id": 1583414}, {"name": "נפטרים_ב-1741", "id": 1583415}, {"name": "נפטרים_ב-1743", "id": 1583417}, {"name": "נפטרים_ב-1744", "id": 1583418}, {"name": "נפטרים_ב-1745", "id": 1583419}, {"name": "נפטרים_ב-1746", "id": 1583420}, {"name": "נפטרים_ב-1747", "id": 1583421}, {"name": "נפטרים_ב-1748", "id": 1583422}, {"name": "נפטרים_ב-1749", "id": 1583423}, {"name": "נפטרים_ב-1750", "id": 1583424}, {"name": "נפטרים_ב-1751", "id": 1583425}, {"name": "נפטרים_ב-1752", "id": 1583426}, {"name": "נפטרים_ב-1753", "id": 1583427}, {"name": "נפטרים_ב-1755", "id": 1583429}, {"name": "נפטרים_ב-1756", "id": 1583430}, {"name": "נפטרים_ב-1758", "id": 1583432}, {"name": "נפטרים_ב-1760", "id": 1583434}, {"name": "נפטרים_ב-1761", "id": 1583435}, {"name": "נפטרים_ב-1762", "id": 1583436}, {"name": "נפטרים_ב-1763", "id": 1583437}, {"name": "נפטרים_ב-1766", "id": 1583440}, {"name": "נפטרים_ב-1768", "id": 1583442}, {"name": "נפטרים_ב-1769", "id": 1583443}, {"name": "נפטרים_ב-1771", "id": 1583445}, {"name": "נפטרים_ב-1772", "id": 1583446}, {"name": "נפטרים_ב-1773", "id": 1583447}, {"name": "נפטרים_ב-1774", "id": 1583448}, {"name": "נפטרים_ב-1775", "id": 1583449}, {"name": "נפטרים_ב-1776", "id": 1583450}, {"name": "נפטרים_ב-1777", "id": 1583451}, {"name": "נפטרים_ב-1778", "id": 1583452}, {"name": "נפטרים_ב-1779", "id": 1583453}, {"name": "נפטרים_ב-1781", "id": 1583455}, {"name": "נפטרים_ב-1782", "id": 1583456}, {"name": "נפטרים_ב-1783", "id": 1583457}, {"name": "נפטרים_ב-1784", "id": 1583458}, {"name": "נפטרים_ב-1785", "id": 1583459}, {"name": "נפטרים_ב-1786", "id": 1583460}, {"name": "נפטרים_ב-1787", "id": 1583461}, {"name": "נפטרים_ב-1790", "id": 1583464}, {"name": "נפטרים_ב-1791", "id": 1583465}, {"name": "נפטרים_ב-1792", "id": 1583466}, {"name": "נפטרים_ב-1793", "id": 1583467}, {"name": "נפטרים_ב-1795", "id": 1583469}, {"name": "ילידי_1703", "id": 1629714}, {"name": "ילידי_1708", "id": 1629719}, {"name": "ילידי_1709", "id": 1629720}, {"name": "ילידי_1711", "id": 1629722}, {"name": "ילידי_1713", "id": 1629724}, {"name": "ילידי_1714", "id": 1629725}, {"name": "ילידי_1717", "id": 1629728}, {"name": "ילידי_1720", "id": 1629731}, {"name": "ילידי_1722", "id": 1629733}, {"name": "ילידי_1724", "id": 1629735}, {"name": "ילידי_1725", "id": 1629736}, {"name": "ילידי_1726", "id": 1629737}, {"name": "ילידי_1729", "id": 1629740}, {"name": "ילידי_1730", "id": 1629741}, {"name": "ילידי_1732", "id": 1629743}, {"name": "ילידי_1734", "id": 1629745}, {"name": "ילידי_1735", "id": 1629746}, {"name": "ילידי_1736", "id": 1629747}, {"name": "ילידי_1737", "id": 1629748}, {"name": "ילידי_1738", "id": 1629749}, {"name": "ילידי_1739", "id": 1629750}, {"name": "ילידי_1740", "id": 1629752}, {"name": "ילידי_1741", "id": 1629753}, {"name": "ילידי_1742", "id": 1629754}, {"name": "ילידי_1743", "id": 1629755}, {"name": "ילידי_1745", "id": 1629758}, {"name": "ילידי_1746", "id": 1629759}, {"name": "ילידי_1747", "id": 1629760}, {"name": "ילידי_1748", "id": 1629761}, {"name": "ילידי_1750", "id": 1629763}, {"name": "ילידי_1753", "id": 1629766}, {"name": "ילידי_1754", "id": 1629767}, {"name": "ילידי_1755", "id": 1629768}, {"name": "ילידי_1756", "id": 1629769}, {"name": "ילידי_1757", "id": 1629770}, {"name": "ילידי_1758", "id": 1629771}, {"name": "ילידי_1759", "id": 1629772}, {"name": "ילידי_1760", "id": 1629773}, {"name": "ילידי_1761", "id": 1629774}, {"name": "ילידי_1764", "id": 1629777}, {"name": "ילידי_1765", "id": 1629778}, {"name": "ילידי_1766", "id": 1629779}, {"name": "ילידי_1767", "id": 1629780}, {"name": "ילידי_1768", "id": 1629781}, {"name": "ילידי_1769", "id": 1629782}, {"name": "ילידי_1770", "id": 1629783}, {"name": "ילידי_1771", "id": 1629784}, {"name": "ילידי_1772", "id": 1629785}, {"name": "ילידי_1773", "id": 1629786}, {"name": "ילידי_1774", "id": 1629787}, {"name": "ילידי_1775", "id": 1629788}, {"name": "ילידי_1776", "id": 1629789}, {"name": "ילידי_1777", "id": 1629790}, {"name": "ילידי_1778", "id": 1629791}, {"name": "ילידי_1779", "id": 1629792}, {"name": "ילידי_1780", "id": 1629793}, {"name": "ילידי_1782", "id": 1629795}, {"name": "ילידי_1783", "id": 1629796}, {"name": "ילידי_1784", "id": 1629797}, {"name": "ילידי_1785", "id": 1629799}, {"name": "ילידי_1786", "id": 1629800}, {"name": "ילידי_1787", "id": 1629801}, {"name": "ילידי_1788", "id": 1629802}, {"name": "ילידי_1789", "id": 1629803}, {"name": "ילידי_1790", "id": 1629804}, {"name": "ילידי_1791", "id": 1629805}, {"name": "ילידי_1792", "id": 1629806}, {"name": "ילידי_1793", "id": 1629807}, {"name": "ילידי_1794", "id": 1629808}, {"name": "ילידי_1795", "id": 1629809}, {"name": "ילידי_1796", "id": 1629810}, {"name": "ילידי_1797", "id": 1629812}, {"name": "ילידי_1798", "id": 1629813}, {"name": "ילידי_1799", "id": 1629814}, {"name": "ילידי_1800", "id": 1629815}, {"name": "נשים_צרפתיות_במאה_ה-18", "id": 1910563}, {"name": "ילידות_1797", "id": 1724684}, {"name": "ילידות_1796", "id": 1724685}, {"name": "ילידות_1768", "id": 1724725}, {"name": "ילידות_1764", "id": 1724843}, {"name": "גרמנים_שנולדו_ב-1797", "id": 1941280}, {"name": "גרמנים_שנולדו_ב-1800", "id": 1943157}, {"name": "גרמנים_שנולדו_ב-1723", "id": 1943543}, {"name": "גרמנים_שנולדו_ב-1786", "id": 1943546}, {"name": "גרמנים_שנולדו_ב-1789", "id": 1943547}, {"name": "גרמנים_שנולדו_ב-1785", "id": 1951375}, {"name": "גרמנים_שנולדו_ב-1784", "id": 1951377}, {"name": "אמריקאים_שנולדו_במאה_ה-18", "id": 1743480}, {"name": "עורכי_דין_אמריקאים_במאה_ה-18", "id": 1918025}]}