{"name": "תחומים_ברפואה", "id": 162388, "predecessors": [{"name": "רפואה", "id": 19539}, {"name": "אקדמיה", "id": 689480}], "successors": [{"name": "נוירולוגיה", "id": 19911}, {"name": "פסיכיאטריה", "id": 31209}, {"name": "רפואת_שיניים", "id": 43362}, {"name": "רפואת_ילדים", "id": 99248}, {"name": "אף_אוזן_וגרון", "id": 158584}, {"name": "כירורגיה", "id": 256635}, {"name": "המטולוגיה", "id": 271705}, {"name": "רפואת_חירום", "id": 346551}, {"name": "אורולוגיה", "id": 569142}, {"name": "אורתופדיה", "id": 610068}, {"name": "רפואת_ריאות", "id": 638282}, {"name": "רפואה_משפטית", "id": 703997}, {"name": "רפואת_עיניים", "id": 720642}, {"name": "גינקולוגיה", "id": 780104}, {"name": "קרדיולוגיה", "id": 826186}, {"name": "אפידמיולוגיה", "id": 882068}, {"name": "בריאות_הציבור", "id": 882069}, {"name": "נוירוכירורגיה", "id": 914979}, {"name": "רפואה_פנימית", "id": 984500}, {"name": "אונקולוגיה", "id": 985208}, {"name": "גרונטולוגיה", "id": 1147976}, {"name": "גריאטריה", "id": 1147996}, {"name": "טרטולוגיה", "id": 1157909}, {"name": "רפואת_פוריות", "id": 1386334}, {"name": "רפואת_נשים", "id": 1443433}, {"name": "גסטרואנטרולוגיה", "id": 1664759}, {"name": "וירולוגיה", "id": 1981878}, {"name": "רופאי_משפחה_ישראלים", "id": 1804626}]}