{"name": "ילידי_1989", "id": 1629866, "predecessors": [{"name": "1989", "id": 41590}, {"name": "המאה_ה-20", "id": 23309}], "successors": [{"name": "ילידות_1989", "id": 1701110}, {"name": "ישראלים_שנולדו_ב-1989", "id": 1637112}, {"name": "אמריקאים_שנולדו_ב-1989", "id": 1638561}, {"name": "בריטים_שנולדו_ב-1989", "id": 1759844}, {"name": "ספרדים_שנולדו_ב-1989", "id": 1841911}, {"name": "גרמנים_שנולדו_ב-1989", "id": 1841924}, {"name": "קרואטים_שנולדו_ב-1989", "id": 1841926}, {"name": "צרפתים_שנולדו_ב-1989", "id": 1841927}, {"name": "איטלקים_שנולדו_ב-1989", "id": 1841932}, {"name": "ברזילאים_שנולדו_ב-1989", "id": 1841937}, {"name": "רוסים_שנולדו_ב-1989", "id": 1841944}, {"name": "הולנדים_שנולדו_ב-1989", "id": 1842044}, {"name": "קנדים_שנולדו_ב-1989", "id": 1842093}, {"name": "אוסטרלים_שנולדו_ב-1989", "id": 1842108}, {"name": "ברזילאים_שנולדו_ב-1987", "id": 1842152}]}