{"name": "ילידי_1875", "id": 1630030, "predecessors": [{"name": "המאה_ה-19_לפי_שנים", "id": 238592}, {"name": "המאה_ה-19", "id": 28943}], "successors": [{"name": "ילידות_1875", "id": 1716021}, {"name": "אמריקאים_שנולדו_ב-1875", "id": 1725122}, {"name": "ישראלים_שנולדו_ב-1875", "id": 1734729}, {"name": "צרפתים_שנולדו_ב-1875", "id": 1836975}, {"name": "בריטים_שנולדו_ב-1875", "id": 1863042}, {"name": "גרמנים_שנולדו_ב-1875", "id": 1926954}, {"name": "הונגרים_שנולדו_ב-1875", "id": 1951699}, {"name": "ארץ-ישראלים_שנולדו_ב-1875", "id": 2083450}]}