{"name": "ישראליות_זוכות_פרסים", "id": 1671454, "predecessors": [{"name": "נשים_זוכות_פרסים", "id": 1402448}, {"name": "מגדר", "id": 26518}], "successors": [{"name": "זוכות_פרס_ישראל", "id": 1477966}, {"name": "ישראליות_זוכות_פרסים:_שירה", "id": 1539246}, {"name": "ישראליות_זוכות_פרסים:_אמנות", "id": 1614839}, {"name": "ישראליות_זוכות_פרסים:_מדע_וטכנולוגיה", "id": 1671453}, {"name": "זוכות_פרס_זאב", "id": 1923885}, {"name": "זוכות_פרס_התיאטרון_הישראלי", "id": 1947216}, {"name": "זוכות_פרס_רוזנבלום", "id": 2142331}, {"name": "כלות_אות_אבירות_מרכז_פרס_לשלום_ולחדשנות", "id": 2314849}, {"name": "יקירות_ירושלים", "id": 1939748}]}