{"name": "מקבלות_תואר_דוקטור_לשם_כבוד", "id": 1893141, "predecessors": [{"name": "נשים_זוכות_פרסים", "id": 1402448}, {"name": "בוגרי_אוניברסיטאות_ומכללות", "id": 1093314}], "successors": [{"name": "מקבלות_תואר_דוקטור_לשם_כבוד_מאוניברסיטת_בן-גוריון_בנגב", "id": 1892790}, {"name": "מקבלות_תואר_דוקטור_לשם_כבוד_מאוניברסיטת_בר-אילן", "id": 1892791}, {"name": "מקבלות_תואר_דוקטור_לשם_כבוד_מאוניברסיטת_חיפה", "id": 1892792}, {"name": "מקבלות_תואר_דוקטור_לשם_כבוד_מאוניברסיטת_תל_אביב", "id": 1892793}, {"name": "מקבלות_תואר_דוקטור_לשם_כבוד_מהאוניברסיטה_העברית_בירושלים", "id": 1984601}]}