{"name": "ישראל:_מוסדות_לימוד", "id": 193618, "predecessors": [{"name": "ישראל:_חינוך", "id": 100037}, {"name": "מוסדות_לימוד_ומחקר", "id": 29090}], "successors": [{"name": "כפרי_נוער", "id": 99386}, {"name": "בוגרי_המכללה_האקדמית_הרצוג", "id": 1951555}, {"name": "בוגרי_בית_הספר_פיק\"א", "id": 1987577}, {"name": "בוגרי_גימנסיה_אחד_העם_(פתח_תקווה)", "id": 1099631}, {"name": "בוגרי_תיכון_ברנר", "id": 1487416}, {"name": "בוגרי_ישיבת_היישוב_החדש", "id": 876267}, {"name": "בוגרי_גימנסיה_הרצליה", "id": 907887}, {"name": "בוגרי_בית_הספר_צייטלין", "id": 982304}, {"name": "בוגרי_גימנסיה_גאולה", "id": 1045551}, {"name": "בוגרי_תיכון_חדש", "id": 1051587}, {"name": "בוגרי_תיכון_עירוני_ה'_(תל_אביב)", "id": 1074424}, {"name": "בוגרי_תיכון_עירוני_א'_(תל_אביב)", "id": 1074425}, {"name": "בוגרי_תיכון_עירוני_י\"ד_(תל_אביב)", "id": 1134139}, {"name": "בוגרי_תיכון_עירוני_ד'_(תל_אביב)", "id": 1160301}, {"name": "בוגרי_תיכון_אליאנס_(תל_אביב)", "id": 1545709}, {"name": "בוגרי_גימנסיה_בלפור", "id": 1956249}, {"name": "בוגרי_התיכון_המקצועי_ע\"ש_מקס_פיין", "id": 1967053}, {"name": "בוגרי_תיכון_עירוני_ט'_(תל_אביב)", "id": 1967057}, {"name": "בוגרי_בית_הספר_הריאלי", "id": 1062542}, {"name": "בוגרי_תיכון_חוגים", "id": 1367270}, {"name": "בוגרי_בסמ\"ת", "id": 1367272}, {"name": "בוגרי_תיכון_קריית_חיים", "id": 1506486}, {"name": "בוגרי_מרכז_חינוך_ליאו_באק", "id": 1571559}, {"name": "בוגרי_תיכון_עירוני_ה'_(חיפה)", "id": 1958562}, {"name": "בוגרי_בית_הספר_אליאנס_(חיפה)", "id": 1960739}, {"name": "בוגרי_ישיבת_נתיב_מאיר", "id": 792091}, {"name": "בוגרי_ישיבת_ירושלים_לצעירים", "id": 988131}, {"name": "בוגרי_ישיבת_חורב-ירושלים", "id": 1055220}, {"name": "בוגרי_תיכון_בויאר", "id": 1060937}, {"name": "בוגרי_תיכון_הימלפרב", "id": 1060938}, {"name": "בוגרי_גימנסיה_רחביה", "id": 1090657}, {"name": "בוגרי_בית_הספר_מעלה", "id": 1207621}, {"name": "בוגרי_התיכון_ליד_האוניברסיטה", "id": 1411936}, {"name": "בוגרי_התיכון_לאמנויות_ע\"ש_צ'ארלס_א'_סמית'", "id": 1650188}, {"name": "בוגרי_תיכון_רנה_קסין", "id": 1925603}, {"name": "בוגרי_תיכון_עירוני_ג'_(ירושלים)", "id": 1987679}, {"name": "בוגרי_התיכון_שליד_האקדמיה_למוסיקה_ולמחול_בירושלים", "id": 2054530}, {"name": "בוגרי_בית_ספר_אליאנס_(ירושלים)", "id": 2089527}, {"name": "בוגרי_תיכון_בליך", "id": 1058403}, {"name": "בוגרי_בית_הספר_אהל_שם", "id": 1089253}, {"name": "מכינות_קדם-צבאיות", "id": 730046}, {"name": "בוגרי_בית_הספר_חביב", "id": 1092649}, {"name": "בוגרי_תיכון_מקיף_יהוד", "id": 1031279}, {"name": "בוגרות_תיכון_חדש", "id": 1754067}, {"name": "בוגרות_גימנסיה_הרצליה", "id": 1754068}, {"name": "בוגרות_תיכון_עירוני_ה'_(תל_אביב)", "id": 1754071}, {"name": "בוגרות_תיכון_עירוני_א'_(תל_אביב)", "id": 1754072}, {"name": "בוגרות_תיכון_עירוני_ד'_(תל_אביב)", "id": 1754073}, {"name": "בוגרות_תיכון_אליאנס_(תל_אביב)", "id": 1754150}, {"name": "בוגרות_התיכון_ליד_האוניברסיטה", "id": 1754154}, {"name": "בוגרות_גימנסיה_רחביה", "id": 1754170}, {"name": "בוגרות_בית_הספר_הריאלי", "id": 1757900}, {"name": "בוגרי_תיכון_מקיף_א'_(באר_שבע)", "id": 1959310}]}