{"name": "קיבוצים", "id": 19708, "predecessors": [{"name": "הקיבוץ", "id": 669731}, {"name": "תנועות_מיישבות", "id": 296887}, {"name": "דמוגרפיה_לפי_מדינה", "id": 859172}], "successors": [{"name": "הקיבוץ_הדתי", "id": 93911}, {"name": "קיבוצי_הקיבוץ_הארצי", "id": 199034}, {"name": "קיבוצים_עירוניים", "id": 211760}, {"name": "קיבוצים_לשעבר", "id": 698938}, {"name": "אנשי_הקיבוץ", "id": 826179}, {"name": "קבוצת_כנרת", "id": 1072231}, {"name": "מעגן_מיכאל", "id": 1175232}, {"name": "משמר_העמק", "id": 1270847}, {"name": "יגור", "id": 1562676}, {"name": "גבעת_ברנר", "id": 1564497}, {"name": "הזורע", "id": 1575270}, {"name": "בארי", "id": 1575827}, {"name": "נירים", "id": 1579409}, {"name": "ניצנים", "id": 1599794}, {"name": "זיקים", "id": 1656626}, {"name": "נשות_הקיבוץ", "id": 1921296}, {"name": "קיבוצי_הקיבוץ_המאוחד", "id": 1923540}, {"name": "תל_יוסף:_אישים", "id": 1430942}, {"name": "קיבוצים_במחוז_חיפה", "id": 1996002}, {"name": "קיבוצים_במחוז_הדרום", "id": 1997231}]}