{"name": "2012", "id": 202082, "predecessors": [{"name": "המאה_ה-21_לפי_שנים", "id": 54429}, {"name": "המאה_ה-21", "id": 41283}], "successors": [{"name": "2012_בספורט", "id": 440959}, {"name": "מכשירים_שהושקו_ב-2012", "id": 991624}, {"name": "מלחמת_האזרחים_בסוריה", "id": 1055536}, {"name": "2012_בפוליטיקה", "id": 1238873}, {"name": "נפטרים_ב-2012", "id": 1573444}, {"name": "נפטרות_ב-2012", "id": 1702567}, {"name": "סרטי_2012", "id": 893441}, {"name": "אלבומי_2012", "id": 971469}, {"name": "שירי_2012", "id": 977453}, {"name": "ספרי_2012", "id": 984542}, {"name": "תוכנות_שהושקו_ב-2012", "id": 991404}, {"name": "אתרי_אינטרנט_שהושקו_ב-2012", "id": 1039714}, {"name": "סינגלים_מ-2012", "id": 1896882}, {"name": "2012_בישראל", "id": 907677}, {"name": "2012_בארצות_הברית", "id": 965705}, {"name": "2012_ברוסיה", "id": 1023105}, {"name": "2012_בממלכה_המאוחדת", "id": 1049387}, {"name": "סיבובי_הופעות_מ-2012", "id": 1537482}, {"name": "להקות_שהתפרקו_בשנת_2012", "id": 1901454}, {"name": "להקות_שהוקמו_בשנת_2012", "id": 1920434}, {"name": "דגמי_מכוניות_שהושקו_ב-2012", "id": 1034238}, {"name": "מאובני_טקסונים_שתוארו_ב-2012", "id": 1825724}, {"name": "כדורגלני_יורו_2012", "id": 1479614}, {"name": "צרפתים_שנפטרו_ב-2012", "id": 1838566}]}