{"name": "ידע", "id": 2188100, "predecessors": [{"name": "זיכרון", "id": 70776}, {"name": "מידע", "id": 58147}, {"name": "פסיכולוגיה_קוגניטיבית", "id": 23515}, {"name": "קוגניציה", "id": 84113}, {"name": "אקדמיה", "id": 689480}], "successors": [{"name": "טכנולוגיה", "id": 21728}, {"name": "סטטיסטיקה", "id": 32600}, {"name": "זיכרון", "id": 70776}, {"name": "סמנטיקה", "id": 306842}, {"name": "ניהול_ידע", "id": 736220}, {"name": "כשלים_לוגיים", "id": 58939}, {"name": "הטיות_קוגניטיביות", "id": 60576}]}