{"name": "אנרגיה", "id": 22501, "predecessors": [{"name": "גדלים_פיזיקליים", "id": 213432}, {"name": "טכנולוגיה", "id": 21728}, {"name": "כלכלה", "id": 22250}], "successors": [{"name": "תרמודינמיקה", "id": 22255}, {"name": "חשמל", "id": 34146}, {"name": "מנועים", "id": 59034}, {"name": "דלק", "id": 66301}, {"name": "אנרגיה_מתחדשת", "id": 363701}, {"name": "חברות_אנרגיה", "id": 622894}, {"name": "חימום", "id": 822231}, {"name": "חיסכון_באנרגיה", "id": 909098}, {"name": "שרי_אנרגיה", "id": 1052744}, {"name": "חום_(פיזיקה)", "id": 2138091}, {"name": "ישראל:_אנרגיה", "id": 445262}, {"name": "ארצות_הברית:_אנרגיה", "id": 1152402}, {"name": "הרשות_הפלסטינית:_אנרגיה", "id": 1886406}, {"name": "תוכנית_הגרעין_של_ברית_המועצות", "id": 1472147}, {"name": "תחנות_כוח_גרעיניות", "id": 876514}]}