{"name": "כדור_הארץ", "id": 245806, "predecessors": [{"name": "מערכת_השמש", "id": 28755}, {"name": "אסטרופיזיקה", "id": 54349}], "successors": [{"name": "מדעי_כדור_הארץ", "id": 19204}, {"name": "משימות_לחקר_הירח", "id": 933424}, {"name": "הירח_באומנות", "id": 1680076}, {"name": "שירים_על_הירח", "id": 2006766}, {"name": "הידרולוגיה", "id": 82198}, {"name": "ספינות_טרופות", "id": 116435}, {"name": "גופי_מים", "id": 245244}, {"name": "אוקיינוגרפיה", "id": 478879}, {"name": "אנטארקטיקה:_איים", "id": 215836}, {"name": "יוון:_איים", "id": 1201119}, {"name": "קוריאה:_היסטוריה", "id": 31546}, {"name": "שירים_בקוריאנית", "id": 1848733}, {"name": "אלבומים_בקוריאנית", "id": 1968162}, {"name": "איים_בים_הקריבי", "id": 43775}, {"name": "אנטארקטיקה:_קרחונים", "id": 1242038}, {"name": "הפיליפינים:_היסטוריה", "id": 36733}, {"name": "אנטארקטיקה:_חופים", "id": 1452134}, {"name": "גאולוגיה", "id": 111221}]}