{"name": "יהודים_הולנדים", "id": 317528, "predecessors": [{"name": "יהדות_הולנד", "id": 154889}, {"name": "דמוגרפיה_לפי_מדינה", "id": 859172}, {"name": "היסטוריה", "id": 21852}], "successors": [{"name": "רבנים_הולנדים", "id": 146585}, {"name": "יהודים_בשואה:_הולנד", "id": 599989}, {"name": "סופרים_יהודים_הולנדים", "id": 1157789}, {"name": "פוליטיקאים_יהודים_הולנדים", "id": 1544549}, {"name": "ישראלים_ילידי_הולנד", "id": 1664800}, {"name": "ספורטאים_יהודים_הולנדים", "id": 1856870}, {"name": "רופאים_יהודים_הולנדים", "id": 1711749}, {"name": "ציירים_יהודים_הולנדים", "id": 1300702}]}