{"name": "יוונים", "id": 37688, "predecessors": [{"name": "עמי_אירופה", "id": 63620}, {"name": "עמים", "id": 23443}, {"name": "ארגוני_כלכלה_בין-לאומיים", "id": 1615041}], "successors": [{"name": "יהודים_יוונים", "id": 359861}, {"name": "אצולה_יוונית", "id": 472932}, {"name": "יוון_העתיקה:_אישים", "id": 587824}, {"name": "יוונים_חסידי_אומות_העולם", "id": 942865}, {"name": "אמריקאים_ממוצא_יווני", "id": 1286518}, {"name": "סלוניקי:_אישים", "id": 1489245}, {"name": "רומנים_ממוצא_יווני", "id": 1541491}, {"name": "פילוסופים_יוונים", "id": 37689}, {"name": "מוזיקאים_יוונים", "id": 109414}, {"name": "סופרים_יוונים", "id": 118322}, {"name": "משוררים_יוונים", "id": 118345}, {"name": "מחזאים_יוונים", "id": 158685}, {"name": "פסלים_יוונים", "id": 257892}, {"name": "מלחינים_יוונים", "id": 314724}, {"name": "רופאים_יוונים", "id": 488109}, {"name": "פוליטיקאים_יוונים", "id": 1069269}, {"name": "מאמני_כדורגל_יוונים", "id": 1421112}, {"name": "ארכימדס", "id": 625525}, {"name": "אסטרונומים_יוונים", "id": 472015}, {"name": "גנרלים_יוונים", "id": 785437}, {"name": "ישראלים_ילידי_יוון", "id": 1563708}, {"name": "אמריקאיות_ממוצא_יווני", "id": 1925855}, {"name": "זמרות_יווניות", "id": 1450865}, {"name": "מתמטיקאים_מיוון_העתיקה", "id": 601945}]}