{"name": "האוקיינוס_ההודי", "id": 43725, "predecessors": [{"name": "אוקיינוסים", "id": 27343}], "successors": [{"name": "איים_באוקיינוס_ההודי", "id": 36004}, {"name": "מצרי_ים_באוקיינוס_ההודי", "id": 1117293}, {"name": "המפרץ_הפרסי", "id": 1137760}, {"name": "האיים_המלדיביים:_אטולים", "id": 1209641}, {"name": "החי_במפרץ_אילת", "id": 1275365}, {"name": "דגי_האוקיינוס_ההודי", "id": 1763707}, {"name": "מגה-פאונה_של_האוקיינוס_ההודי", "id": 1889780}, {"name": "עופות_האוקיינוס_ההודי", "id": 1895395}, {"name": "בעלי_חיים_ימיים_בצפון_אוסטרליה", "id": 2052102}]}