{"name": "מפיקי_קולנוע", "id": 46467, "predecessors": [{"name": "מקצועות", "id": 24675}], "successors": [{"name": "מפיקות_קולנוע", "id": 1615215}, {"name": "מפיקי_קולנוע_אמריקאים", "id": 46466}, {"name": "מפיקי_קולנוע_בריטים", "id": 46472}, {"name": "מפיקי_קולנוע_ישראלים", "id": 159815}, {"name": "מפיקי_קולנוע_צרפתים", "id": 247814}, {"name": "מפיקי_קולנוע_יהודים", "id": 285447}, {"name": "מפיקי_קולנוע_קנדים", "id": 289122}, {"name": "מפיקי_קולנוע_הודים", "id": 1482828}, {"name": "מפיקי_קולנוע_איטלקים", "id": 1482843}, {"name": "מפיקי_קולנוע_רוסים", "id": 1565286}, {"name": "מפיקות_קולנוע_ניגריות", "id": 1645534}]}