{"name": "הנגב", "id": 47558, "predecessors": [{"name": "ארץ_ישראל:_אזורים", "id": 282882}, {"name": "ישראל:_גאוגרפיה", "id": 1418331}], "successors": [{"name": "הר_חברון", "id": 546736}, {"name": "הנגב:_הרים", "id": 553057}, {"name": "הנגב:_אתרים_ארכאולוגיים", "id": 1030467}, {"name": "הערבה", "id": 1030512}, {"name": "הנגב:_נחלים", "id": 1058145}, {"name": "הנגב:_יישובים", "id": 1082503}, {"name": "באר_שבע:_מבנים", "id": 402649}, {"name": "באר_שבע:_אישים", "id": 579303}, {"name": "אילת:_אישים", "id": 1075740}, {"name": "עומר:_אישים", "id": 1559573}]}