{"name": "משטרה", "id": 487081, "predecessors": [{"name": "מינהל_ציבורי", "id": 959929}, {"name": "חברה", "id": 353812}], "successors": [{"name": "חקירה", "id": 487079}, {"name": "שוטרים", "id": 656394}, {"name": "מקצועות_אכיפת_החוק", "id": 805695}, {"name": "יחידות_משטרתיות_ללחימה_בטרור", "id": 990921}, {"name": "סרטי_משטרה", "id": 994723}, {"name": "סדרות_משטרה_ופשע", "id": 1078665}, {"name": "ארגונים_משטרתיים", "id": 1165588}, {"name": "חילות_משטרה_צבאית", "id": 1355334}, {"name": "אלימות_משטרתית", "id": 1866516}, {"name": "שוטרות_ישראליות", "id": 1847367}, {"name": "שרי_המשטרה_וביטחון_הפנים_בממשלות_ישראל", "id": 587924}]}