{"name": "מלחמת_האזרחים_בספרד", "id": 565052, "predecessors": [{"name": "בין_שתי_מלחמות_העולם", "id": 623014}, {"name": "הרפובליקה_הספרדית_השנייה", "id": 462912}, {"name": "מלחמות_אזרחים_באירופה", "id": 1205293}, {"name": "מלחמות_ספרד", "id": 315049}, {"name": "ספרד:_העת_החדשה", "id": 1638356}], "successors": [{"name": "הבריגדות_הבין-לאומיות", "id": 1975087}, {"name": "אישים_שנהרגו_במלחמת_האזרחים_בספרד", "id": 1606227}, {"name": "יהודים_במלחמת_האזרחים_בספרד", "id": 1975092}, {"name": "סובייטים_במלחמת_האזרחים_בספרד", "id": 1975102}, {"name": "ספרדים_במלחמת_האזרחים_בספרד", "id": 1975106}]}