{"name": "צרפת:_תרבות", "id": 57678, "predecessors": [{"name": "אירופה:_תרבות", "id": 355384}, {"name": "מדינות_העולם", "id": 18593}, {"name": "ארגוני_כלכלה_בין-לאומיים", "id": 1615041}], "successors": [{"name": "ספרות_צרפתית", "id": 61297}, {"name": "מוזיקה_צרפתית", "id": 159487}, {"name": "פרסים_צרפתיים", "id": 318823}, {"name": "המטבח_הצרפתי", "id": 352238}, {"name": "צרפת:_עיתונים", "id": 436811}, {"name": "צרפת:_עיטורים", "id": 1101266}, {"name": "צרפת_באירוויזיון", "id": 1688180}, {"name": "סרטים_שעלילתם_מתרחשת_בצרפת", "id": 1946924}, {"name": "במאי_קולנוע_צרפתים", "id": 46462}, {"name": "שחקני_קולנוע_וטלוויזיה_צרפתים", "id": 79206}, {"name": "סרטים_צרפתיים", "id": 158912}, {"name": "תסריטאי_קולנוע_צרפתים", "id": 191773}, {"name": "מפיקי_קולנוע_צרפתים", "id": 247814}, {"name": "זוכי_פרס_סזאר", "id": 635659}, {"name": "זוכי_פרס_לומייר", "id": 1327850}, {"name": "חידושים_אמריקאיים_לסרטים_צרפתיים", "id": 1961355}, {"name": "זוכות_פרס_סזאר", "id": 2102184}, {"name": "מחזאים_צרפתים", "id": 117489}, {"name": "שחקני_תיאטרון_צרפתים", "id": 157547}, {"name": "במאי_תיאטרון_צרפתים", "id": 1327232}, {"name": "צרפתית", "id": 615453}, {"name": "אמנים_צרפתים", "id": 326759}, {"name": "בעלות_סלונים_ספרותיים", "id": 1137813}, {"name": "מבקרי_אמנות_צרפתים", "id": 1172737}, {"name": "רומנים_המתרחשים_בפריז", "id": 1331140}, {"name": "שירים_על_פריז", "id": 1948910}]}