{"name": "כלים_ומכשירים_(מזון)", "id": 60177, "predecessors": [{"name": "כלים", "id": 639817}, {"name": "מזון", "id": 18254}, {"name": "מטבח", "id": 1319865}, {"name": "מכונות", "id": 363698}], "successors": [{"name": "מכשירי_מטבח", "id": 368468}, {"name": "אמצעי_חימום_והכנת_מזון", "id": 368471}, {"name": "ציוד_בר", "id": 368477}, {"name": "כלי_אכילה", "id": 368478}, {"name": "כלי_עבודה_במטבח", "id": 368486}, {"name": "כלי_הגשה", "id": 368490}, {"name": "כלי_בישול", "id": 368499}, {"name": "כלי_קיבול", "id": 368504}]}