{"name": "כדורגלנים_צרפתים", "id": 67858, "predecessors": [{"name": "צרפת:_כדורגל", "id": 1092350}, {"name": "אירופה", "id": 35355}, {"name": "ספורט", "id": 23164}], "successors": [{"name": "חלוצי_כדורגל_צרפתים", "id": 579716}, {"name": "קשרי_כדורגל_צרפתים", "id": 579770}, {"name": "שוערי_כדורגל_צרפתים", "id": 910760}, {"name": "מגני_כדורגל_צרפתים", "id": 920187}, {"name": "בלמי_כדורגל_צרפתים", "id": 1188250}, {"name": "כדורגלני_נבחרת_צרפת", "id": 1272665}, {"name": "פריז:_כדורגלנים", "id": 1968932}, {"name": "מרסיי:_כדורגלנים", "id": 1968950}, {"name": "ליון:_כדורגלנים", "id": 1968956}, {"name": "כדורגלנים_צרפתים_באולימפיאדת_טוקיו_(2020)", "id": 2208569}]}