{"name": "פיזיולוגיה", "id": 69618, "predecessors": [{"name": "רפואה", "id": 19539}, {"name": "תחומים_בביולוגיה", "id": 63976}], "successors": [{"name": "הורמונים", "id": 23224}, {"name": "מטבוליזם", "id": 63599}, {"name": "חושים", "id": 84122}, {"name": "שינה", "id": 116623}, {"name": "רפלקסים", "id": 139407}, {"name": "מערכות_גוף", "id": 227154}, {"name": "פיזיולוגיה_של_הצמח", "id": 235156}, {"name": "אלקטרופיזיולוגיה", "id": 291590}, {"name": "נשימה", "id": 300046}, {"name": "היריון_ולידה", "id": 408945}, {"name": "פיזיולוגים", "id": 602807}, {"name": "נוזלי_גוף", "id": 657235}, {"name": "תרמורגולציה", "id": 1622797}]}