{"name": "ערביי_ישראל", "id": 80470, "predecessors": [{"name": "קבוצות_בחברה_הישראלית", "id": 314473}], "successors": [{"name": "יישובים_ערביים_בישראל", "id": 108556}, {"name": "ערבים_ישראלים", "id": 143117}, {"name": "בדואים", "id": 191478}, {"name": "תרבות_ערבית_בישראל", "id": 865123}, {"name": "שותפות_יהודית-ערבית_בישראל", "id": 1138480}, {"name": "ערביי_ישראל:_ארגונים", "id": 1175754}, {"name": "הגירות_מצד_מוסלמים_לארץ_ישראל", "id": 1660794}, {"name": "פיגועים_שבוצעו_על_ידי_ערבים-ישראלים", "id": 1976090}, {"name": "טרור_ערבי_בישראל", "id": 2196096}]}