{"name": "יצירות_המאה_ה-19", "id": 958499, "predecessors": [{"name": "המאה_ה-19", "id": 28943}, {"name": "מאות", "id": 46374}], "successors": [{"name": "המלחמות_הנפוליאוניות:_אמנות_והסכמים", "id": 435685}, {"name": "ספרי_המאה_ה-19", "id": 667627}, {"name": "מחזות_מהמאה_ה-19", "id": 699200}, {"name": "ציורים_מהמאה_ה-19", "id": 958643}, {"name": "שירי_המאה_ה-19", "id": 1001772}, {"name": "מחזות_משנות_ה-1900", "id": 805625}, {"name": "ציורים_משנות_ה-1900", "id": 958936}, {"name": "ספרי_1902", "id": 667653}, {"name": "ספרי_1906", "id": 667657}, {"name": "ספרי_1908", "id": 667659}, {"name": "ספרי_1909", "id": 667660}, {"name": "ספרי_1886", "id": 1387767}, {"name": "ספרי_1888", "id": 1387769}]}